lmt/__init__.py
lmt/generate.py
lmt/layers/__init__.py
lmt/layers/attention/__init__.py
lmt/layers/attention/causal_attention.py
lmt/layers/attention/multihead_attention.py
lmt/layers/attention/self_attention.py
lmt/layers/transformers/__init__.py
lmt/layers/transformers/ff.py
lmt/layers/transformers/transformer.py
lmt/models/__init__.py
lmt/models/config.py
lmt/models/gpt/__init__.py
lmt/models/gpt/gpt.py
lmt/models/utils.py
lmt/tokenizer/__init__.py
lmt/tokenizer/base.py
lmt/tokenizer/bpe.py
lmt/tokenizer/naive.py
lmt/training/__init__.py
lmt/training/config.py
lmt/training/dataloaders.py
lmt/training/datasets.py
lmt/training/loss.py
lmt/training/trainer.py
language_modeling_transformers-0.2.8.dist-info/METADATA
language_modeling_transformers-0.2.8.dist-info/WHEEL
language_modeling_transformers-0.2.8.dist-info/licenses/LICENSE
language_modeling_transformers-0.2.8.dist-info/RECORD
